Workbook

Sheet Assumptions
A1: INVERTA — Bunny Stream cost model
A2: Blue cells are inputs. Yellow cells are the ones to verify against Bunny's current pricing page before trusting the total.
A4: CONTENT
A5: Lessons in the program | B5: 20 | C5: Video sessions with a recording.
A6: Average lesson length (minutes) | B6: 15
A7: Total content (minutes) | B7: =B5*B6 | C7: Drives storage, not delivery.
A9: AUDIENCE
A10: Students per month | B10: 30 | C10: Concurrent cohort actively watching.
A11: Rewatch factor | B11: 1.3 | C11: 1.0 = each student watches everything exactly once. 1.3 assumes 30% revisiting.
A12: Minutes delivered per month | B12: =B7*B10*B11 | C12: =content x students x rewatch.
A14: ENCODING
A15: Delivered size (MB per minute) | B15: 5 | C15: Screencast at ~650 kbps. Full-motion video would be 15-25.
A16: Storage ladder multiplier | B16: 2.5 | C16: Bunny stores several renditions per source. 1.0 would be a single file.
A17: GB delivered per month | B17: =B12*B15/1024
A18: GB stored | B18: =B7*B15*B16/1024 | C18: One-off, not per month — content accumulates as you add lessons.
A20: BUNNY STREAM RATES — VERIFY THESE
A21: Storage ($ per GB per month) | B21: 0.01 | C21: Bunny Stream storage rate.
A22: Delivery ($ per GB) | B22: 0.03 | C22: Asia & Oceania tier — higher than EU/NA. This is the number most likely to be wrong.
A23: Minimum monthly charge ($) | B23: 1 | C23: Bunny applies a monthly floor; small accounts pay it.
A25: COMMERCIAL
A26: USD to IDR | B26: 16000 | C26: For the rupiah view only.
A27: Program price (IDR) | B27: 1500000 | C27: KAK section 17 item 5 — still a placeholder.
A29: Sources
A30: Rates: Bunny.net pricing page — not verified by Claude; my pricing knowledge has a cutoff and video rates change. Content, audience and price figures: supplied by the user (30 students/month, screencast lessons).
A31: Encoding figures are estimates for screen-recorded content, not measured from your actual files. Re-measure once you have one real exported lesson.

Sheet Monthly Cost
A1: Monthly cost — Bunny Stream
A2: Every figure below is a formula off the Assumptions sheet. Change an input there and this recalculates.
A4: Line item | B4: Quantity | C4: Unit | D4: Rate | E4: Cost (USD)
A5: Storage | B5: ='Assumptions'!B18 | C5: GB | D5: ='Assumptions'!B21 | E5: =B5*D5
A6: Delivery | B6: ='Assumptions'!B17 | C6: GB/month | D6: ='Assumptions'!B22 | E6: =B6*D6
A7: Subtotal | E7: =SUM(E5:E6)
A8: Top-up to monthly minimum | C8: applied | E8: =MAX(0,'Assumptions'!B23-E7)
A10: TOTAL (USD / month) | E10: =E7+E8
A11: TOTAL (IDR / month) | E11: =E10*'Assumptions'!B26
A14: Per student
A15: Video cost per student (USD) | E15: =IF('Assumptions'!B10=0,0,E10/'Assumptions'!B10)
A16: Video cost per student (IDR) | E16: =E15*'Assumptions'!B26
A17: Program price (IDR) | E17: ='Assumptions'!B27
A18: Video cost as % of price | E18: =IF('Assumptions'!B27=0,0,E16/'Assumptions'!B27)
A20: What this does NOT include
A21: - Producing the videos — recording, editing, and the person doing it. Almost certainly your largest real cost.
A22: - Payment gateway fees (a PSP takes a percentage of every enrollment — model separately against revenue).
A23: - SES email, R2 audio storage, and the server itself. Small, but not zero.
A24: - One-off encoding: Bunny includes transcoding in Stream, so there is no separate line for it.

Sheet Sensitivity
A1: Cost by cohort size
A2: Only the student count varies; every other assumption is held from the Assumptions sheet. Storage is fixed, so the total is almost entirely delivery.
A4: Students/month | B4: Minutes delivered | C4: GB delivered | D4: Delivery (USD) | E4: Storage (USD) | F4: TOTAL (USD/mo) | G4: TOTAL (IDR/mo)
A5: 10 | B5: =A5*'Assumptions'!$B$7*'Assumptions'!$B$11 | C5: =B5*'Assumptions'!$B$15/1024 | D5: =C5*'Assumptions'!$B$22 | E5: ='Assumptions'!$B$18*'Assumptions'!$B$21 | F5: =MAX(D5+E5,'Assumptions'!$B$23) | G5: =F5*'Assumptions'!$B$26
A6: 20 | B6: =A6*'Assumptions'!$B$7*'Assumptions'!$B$11 | C6: =B6*'Assumptions'!$B$15/1024 | D6: =C6*'Assumptions'!$B$22 | E6: ='Assumptions'!$B$18*'Assumptions'!$B$21 | F6: =MAX(D6+E6,'Assumptions'!$B$23) | G6: =F6*'Assumptions'!$B$26
A7: 30 | B7: =A7*'Assumptions'!$B$7*'Assumptions'!$B$11 | C7: =B7*'Assumptions'!$B$15/1024 | D7: =C7*'Assumptions'!$B$22 | E7: ='Assumptions'!$B$18*'Assumptions'!$B$21 | F7: =MAX(D7+E7,'Assumptions'!$B$23) | G7: =F7*'Assumptions'!$B$26
A8: 50 | B8: =A8*'Assumptions'!$B$7*'Assumptions'!$B$11 | C8: =B8*'Assumptions'!$B$15/1024 | D8: =C8*'Assumptions'!$B$22 | E8: ='Assumptions'!$B$18*'Assumptions'!$B$21 | F8: =MAX(D8+E8,'Assumptions'!$B$23) | G8: =F8*'Assumptions'!$B$26
A9: 100 | B9: =A9*'Assumptions'!$B$7*'Assumptions'!$B$11 | C9: =B9*'Assumptions'!$B$15/1024 | D9: =C9*'Assumptions'!$B$22 | E9: ='Assumptions'!$B$18*'Assumptions'!$B$21 | F9: =MAX(D9+E9,'Assumptions'!$B$23) | G9: =F9*'Assumptions'!$B$26
A10: 200 | B10: =A10*'Assumptions'!$B$7*'Assumptions'!$B$11 | C10: =B10*'Assumptions'!$B$15/1024 | D10: =C10*'Assumptions'!$B$22 | E10: ='Assumptions'!$B$18*'Assumptions'!$B$21 | F10: =MAX(D10+E10,'Assumptions'!$B$23) | G10: =F10*'Assumptions'!$B$26
A11: 500 | B11: =A11*'Assumptions'!$B$7*'Assumptions'!$B$11 | C11: =B11*'Assumptions'!$B$15/1024 | D11: =C11*'Assumptions'!$B$22 | E11: ='Assumptions'!$B$18*'Assumptions'!$B$21 | F11: =MAX(D11+E11,'Assumptions'!$B$23) | G11: =F11*'Assumptions'!$B$26
A13: Highlighted row is your stated case: 30 students/month.
A14: Storage is fixed, so the total is almost entirely delivery and scales linearly with students. The monthly minimum only binds below about 17 students — at 10 students you pay the floor, not usage.
A15: Formulas were checked cell-by-cell and cross-computed in Python, but NOT recalculated by a spreadsheet engine (no LibreOffice on the machine that built this). Open it once and confirm the totals match the figures quoted in chat.
